qualifyr/__init__.py
qualifyr/bactinspector_file.py
qualifyr/conditions_file.py
qualifyr/confindr_file.py
qualifyr/fastqc_summary_file.py
qualifyr/file_size_check_file.py
qualifyr/html_report.py
qualifyr/quality_check.py
qualifyr/quality_file.py
qualifyr/quast_file.py
qualifyr/run_qualifyr.py
qualifyr/text_report.py
qualifyr/utility.py
qualifyr/html_report/assets/css/dataTables.semanticui.min.css
qualifyr/html_report/assets/css/semantic.min.css
qualifyr/html_report/assets/fonts/icons.eot
qualifyr/html_report/assets/fonts/icons.svg
qualifyr/html_report/assets/fonts/icons.ttf
qualifyr/html_report/assets/fonts/icons.woff
qualifyr/html_report/assets/fonts/icons.woff2
qualifyr/html_report/assets/images/details_close.png
qualifyr/html_report/assets/images/details_open.png
qualifyr/html_report/assets/js/dataTables.semanticui.min.js
qualifyr/html_report/assets/js/jquery-3.3.1.min.js
qualifyr/html_report/assets/js/jquery.dataTables.min.js
qualifyr/html_report/assets/js/semantic.dropdown.min.js
qualifyr/html_report/assets/js/semantic.transition.min.js
qualifyr/html_report/templates/main.html
QualiFyr-1.4.6.dist-info/LICENSE
QualiFyr-1.4.6.dist-info/METADATA
QualiFyr-1.4.6.dist-info/WHEEL
QualiFyr-1.4.6.dist-info/entry_points.txt
QualiFyr-1.4.6.dist-info/top_level.txt
QualiFyr-1.4.6.dist-info/RECORD
