Metadata-Version: 2.1
Name: QualiFyr
Version: 1.4.6
Summary: Package to read in output files relating to quality and assess overall pass/fail.
Home-page: UNKNOWN
Author: Anthony Underwood
Author-email: au3@sanger.ac.uk
License: MIT
Platform: UNKNOWN
Classifier: Development Status :: 3 - Alpha
Classifier: Intended Audience :: Science/Research
Classifier: License :: OSI Approved :: MIT License
Classifier: Programming Language :: Python :: 3
Requires-Dist: pyyaml (==5.4.1)
Requires-Dist: colorlog (==6.6.0)
Requires-Dist: jinja2 (==3.0.3)
